{
  "500px": true,
  "accessible-icon": true,
  "accusoft": true,
  "acquisitions-incorporated": true,
  "ad": true,
  "address-book": true,
  "address-card": true,
  "adjust": true,
  "adn": true,
  "adversal": true,
  "affiliatetheme": true,
  "air-freshener": true,
  "airbnb": true,
  "algolia": true,
  "align-center": true,
  "align-justify": true,
  "align-left": true,
  "align-right": true,
  "alipay": true,
  "allergies": true,
  "amazon": true,
  "amazon-pay": true,
  "ambulance": true,
  "american-sign-language-interpreting": true,
  "amilia": true,
  "anchor": true,
  "android": true,
  "angellist": true,
  "angle-double-down": true,
  "angle-double-left": true,
  "angle-double-right": true,
  "angle-double-up": true,
  "angle-down": true,
  "angle-left": true,
  "angle-right": true,
  "angle-up": true,
  "angry": true,
  "angrycreative": true,
  "angular": true,
  "ankh": true,
  "app-store": true,
  "app-store-ios": true,
  "apper": true,
  "apple": true,
  "apple-alt": true,
  "apple-pay": true,
  "archive": true,
  "archway": true,
  "arrow-alt-circle-down": true,
  "arrow-alt-circle-left": true,
  "arrow-alt-circle-right": true,
  "arrow-alt-circle-up": true,
  "arrow-circle-down": true,
  "arrow-circle-left": true,
  "arrow-circle-right": true,
  "arrow-circle-up": true,
  "arrow-down": true,
  "arrow-left": true,
  "arrow-right": true,
  "arrow-up": true,
  "arrows-alt": true,
  "arrows-alt-h": true,
  "arrows-alt-v": true,
  "artstation": true,
  "assistive-listening-systems": true,
  "asterisk": true,
  "asymmetrik": true,
  "at": true,
  "atlas": true,
  "atlassian": true,
  "atom": true,
  "audible": true,
  "audio-description": true,
  "autoprefixer": true,
  "avianex": true,
  "aviato": true,
  "award": true,
  "aws": true,
  "baby": true,
  "baby-carriage": true,
  "backspace": true,
  "backward": true,
  "bacon": true,
  "bacteria": true,
  "bacterium": true,
  "bahai": true,
  "balance-scale": true,
  "balance-scale-left": true,
  "balance-scale-right": true,
  "ban": true,
  "band-aid": true,
  "bandcamp": true,
  "barcode": true,
  "bars": true,
  "baseball-ball": true,
  "basketball-ball": true,
  "bath": true,
  "battery-empty": true,
  "battery-full": true,
  "battery-half": true,
  "battery-quarter": true,
  "battery-three-quarters": true,
  "battle-net": true,
  "bed": true,
  "beer": true,
  "behance": true,
  "behance-square": true,
  "bell": true,
  "bell-slash": true,
  "bezier-curve": true,
  "bible": true,
  "bicycle": true,
  "biking": true,
  "bimobject": true,
  "binoculars": true,
  "biohazard": true,
  "birthday-cake": true,
  "bitbucket": true,
  "bitcoin": true,
  "bity": true,
  "black-tie": true,
  "blackberry": true,
  "blender": true,
  "blender-phone": true,
  "blind": true,
  "blog": true,
  "blogger": true,
  "blogger-b": true,
  "bluetooth": true,
  "bluetooth-b": true,
  "bold": true,
  "bolt": true,
  "bomb": true,
  "bone": true,
  "bong": true,
  "book": true,
  "book-dead": true,
  "book-medical": true,
  "book-open": true,
  "book-reader": true,
  "bookmark": true,
  "bootstrap": true,
  "border-all": true,
  "border-none": true,
  "border-style": true,
  "bowling-ball": true,
  "box": true,
  "box-open": true,
  "box-tissue": true,
  "boxes": true,
  "braille": true,
  "brain": true,
  "bread-slice": true,
  "briefcase": true,
  "briefcase-medical": true,
  "broadcast-tower": true,
  "broom": true,
  "brush": true,
  "btc": true,
  "buffer": true,
  "bug": true,
  "building": true,
  "bullhorn": true,
  "bullseye": true,
  "burn": true,
  "buromobelexperte": true,
  "bus": true,
  "bus-alt": true,
  "business-time": true,
  "buy-n-large": true,
  "buysellads": true,
  "calculator": true,
  "calendar": true,
  "calendar-alt": true,
  "calendar-check": true,
  "calendar-day": true,
  "calendar-minus": true,
  "calendar-plus": true,
  "calendar-times": true,
  "calendar-week": true,
  "camera": true,
  "camera-retro": true,
  "campground": true,
  "canadian-maple-leaf": true,
  "candy-cane": true,
  "cannabis": true,
  "capsules": true,
  "car": true,
  "car-alt": true,
  "car-battery": true,
  "car-crash": true,
  "car-side": true,
  "caravan": true,
  "caret-down": true,
  "caret-left": true,
  "caret-right": true,
  "caret-square-down": true,
  "caret-square-left": true,
  "caret-square-right": true,
  "caret-square-up": true,
  "caret-up": true,
  "carrot": true,
  "cart-arrow-down": true,
  "cart-plus": true,
  "cash-register": true,
  "cat": true,
  "cc-amazon-pay": true,
  "cc-amex": true,
  "cc-apple-pay": true,
  "cc-diners-club": true,
  "cc-discover": true,
  "cc-jcb": true,
  "cc-mastercard": true,
  "cc-paypal": true,
  "cc-stripe": true,
  "cc-visa": true,
  "centercode": true,
  "centos": true,
  "certificate": true,
  "chair": true,
  "chalkboard": true,
  "chalkboard-teacher": true,
  "charging-station": true,
  "chart-area": true,
  "chart-bar": true,
  "chart-line": true,
  "chart-pie": true,
  "check": true,
  "check-circle": true,
  "check-double": true,
  "check-square": true,
  "cheese": true,
  "chess": true,
  "chess-bishop": true,
  "chess-board": true,
  "chess-king": true,
  "chess-knight": true,
  "chess-pawn": true,
  "chess-queen": true,
  "chess-rook": true,
  "chevron-circle-down": true,
  "chevron-circle-left": true,
  "chevron-circle-right": true,
  "chevron-circle-up": true,
  "chevron-down": true,
  "chevron-left": true,
  "chevron-right": true,
  "chevron-up": true,
  "child": true,
  "chrome": true,
  "chromecast": true,
  "church": true,
  "circle": true,
  "circle-notch": true,
  "city": true,
  "clinic-medical": true,
  "clipboard": true,
  "clipboard-check": true,
  "clipboard-list": true,
  "clock": true,
  "clone": true,
  "closed-captioning": true,
  "cloud": true,
  "cloud-download-alt": true,
  "cloud-meatball": true,
  "cloud-moon": true,
  "cloud-moon-rain": true,
  "cloud-rain": true,
  "cloud-showers-heavy": true,
  "cloud-sun": true,
  "cloud-sun-rain": true,
  "cloud-upload-alt": true,
  "cloudflare": true,
  "cloudscale": true,
  "cloudsmith": true,
  "cloudversify": true,
  "cocktail": true,
  "code": true,
  "code-branch": true,
  "codepen": true,
  "codiepie": true,
  "coffee": true,
  "cog": true,
  "cogs": true,
  "coins": true,
  "columns": true,
  "comment": true,
  "comment-alt": true,
  "comment-dollar": true,
  "comment-dots": true,
  "comment-medical": true,
  "comment-slash": true,
  "comments": true,
  "comments-dollar": true,
  "compact-disc": true,
  "compass": true,
  "compress": true,
  "compress-alt": true,
  "compress-arrows-alt": true,
  "concierge-bell": true,
  "confluence": true,
  "connectdevelop": true,
  "contao": true,
  "cookie": true,
  "cookie-bite": true,
  "copy": true,
  "copyright": true,
  "cotton-bureau": true,
  "couch": true,
  "cpanel": true,
  "creative-commons": true,
  "creative-commons-by": true,
  "creative-commons-nc": true,
  "creative-commons-nc-eu": true,
  "creative-commons-nc-jp": true,
  "creative-commons-nd": true,
  "creative-commons-pd": true,
  "creative-commons-pd-alt": true,
  "creative-commons-remix": true,
  "creative-commons-sa": true,
  "creative-commons-sampling": true,
  "creative-commons-sampling-plus": true,
  "creative-commons-share": true,
  "creative-commons-zero": true,
  "credit-card": true,
  "critical-role": true,
  "crop": true,
  "crop-alt": true,
  "cross": true,
  "crosshairs": true,
  "crow": true,
  "crown": true,
  "crutch": true,
  "css3": true,
  "css3-alt": true,
  "cube": true,
  "cubes": true,
  "cut": true,
  "cuttlefish": true,
  "d-and-d": true,
  "d-and-d-beyond": true,
  "dailymotion": true,
  "dashcube": true,
  "database": true,
  "deaf": true,
  "deezer": true,
  "delicious": true,
  "democrat": true,
  "deploydog": true,
  "deskpro": true,
  "desktop": true,
  "dev": true,
  "deviantart": true,
  "dharmachakra": true,
  "dhl": true,
  "diagnoses": true,
  "diaspora": true,
  "dice": true,
  "dice-d20": true,
  "dice-d6": true,
  "dice-five": true,
  "dice-four": true,
  "dice-one": true,
  "dice-six": true,
  "dice-three": true,
  "dice-two": true,
  "digg": true,
  "digital-ocean": true,
  "digital-tachograph": true,
  "directions": true,
  "discord": true,
  "discourse": true,
  "disease": true,
  "divide": true,
  "dizzy": true,
  "dna": true,
  "dochub": true,
  "docker": true,
  "dog": true,
  "dollar-sign": true,
  "dolly": true,
  "dolly-flatbed": true,
  "donate": true,
  "door-closed": true,
  "door-open": true,
  "dot-circle": true,
  "dove": true,
  "download": true,
  "draft2digital": true,
  "drafting-compass": true,
  "dragon": true,
  "draw-polygon": true,
  "dribbble": true,
  "dribbble-square": true,
  "dropbox": true,
  "drum": true,
  "drum-steelpan": true,
  "drumstick-bite": true,
  "drupal": true,
  "dumbbell": true,
  "dumpster": true,
  "dumpster-fire": true,
  "dungeon": true,
  "dyalog": true,
  "earlybirds": true,
  "ebay": true,
  "edge": true,
  "edge-legacy": true,
  "edit": true,
  "egg": true,
  "eject": true,
  "elementor": true,
  "ellipsis-h": true,
  "ellipsis-v": true,
  "ello": true,
  "ember": true,
  "empire": true,
  "envelope": true,
  "envelope-open": true,
  "envelope-open-text": true,
  "envelope-square": true,
  "envira": true,
  "equals": true,
  "eraser": true,
  "erlang": true,
  "ethereum": true,
  "ethernet": true,
  "etsy": true,
  "euro-sign": true,
  "evernote": true,
  "exchange-alt": true,
  "exclamation": true,
  "exclamation-circle": true,
  "exclamation-triangle": true,
  "expand": true,
  "expand-alt": true,
  "expand-arrows-alt": true,
  "expeditedssl": true,
  "external-link-alt": true,
  "external-link-square-alt": true,
  "eye": true,
  "eye-dropper": true,
  "eye-slash": true,
  "facebook": true,
  "facebook-f": true,
  "facebook-messenger": true,
  "facebook-square": true,
  "fan": true,
  "fantasy-flight-games": true,
  "fast-backward": true,
  "fast-forward": true,
  "faucet": true,
  "fax": true,
  "feather": true,
  "feather-alt": true,
  "fedex": true,
  "fedora": true,
  "female": true,
  "fighter-jet": true,
  "figma": true,
  "file": true,
  "file-alt": true,
  "file-archive": true,
  "file-audio": true,
  "file-code": true,
  "file-contract": true,
  "file-csv": true,
  "file-download": true,
  "file-excel": true,
  "file-export": true,
  "file-image": true,
  "file-import": true,
  "file-invoice": true,
  "file-invoice-dollar": true,
  "file-medical": true,
  "file-medical-alt": true,
  "file-pdf": true,
  "file-powerpoint": true,
  "file-prescription": true,
  "file-signature": true,
  "file-upload": true,
  "file-video": true,
  "file-word": true,
  "fill": true,
  "fill-drip": true,
  "film": true,
  "filter": true,
  "fingerprint": true,
  "fire": true,
  "fire-alt": true,
  "fire-extinguisher": true,
  "firefox": true,
  "firefox-browser": true,
  "first-aid": true,
  "first-order": true,
  "first-order-alt": true,
  "firstdraft": true,
  "fish": true,
  "fist-raised": true,
  "flag": true,
  "flag-checkered": true,
  "flag-usa": true,
  "flask": true,
  "flickr": true,
  "flipboard": true,
  "flushed": true,
  "fly": true,
  "folder": true,
  "folder-minus": true,
  "folder-open": true,
  "folder-plus": true,
  "font": true,
  "font-awesome": true,
  "font-awesome-alt": true,
  "font-awesome-flag": true,
  "font-awesome-logo-full": true,
  "fonticons": true,
  "fonticons-fi": true,
  "football-ball": true,
  "fort-awesome": true,
  "fort-awesome-alt": true,
  "forumbee": true,
  "forward": true,
  "foursquare": true,
  "free-code-camp": true,
  "freebsd": true,
  "frog": true,
  "frown": true,
  "frown-open": true,
  "fulcrum": true,
  "funnel-dollar": true,
  "futbol": true,
  "galactic-republic": true,
  "galactic-senate": true,
  "gamepad": true,
  "gas-pump": true,
  "gavel": true,
  "gem": true,
  "genderless": true,
  "get-pocket": true,
  "gg": true,
  "gg-circle": true,
  "ghost": true,
  "gift": true,
  "gifts": true,
  "git": true,
  "git-alt": true,
  "git-square": true,
  "github": true,
  "github-alt": true,
  "github-square": true,
  "gitkraken": true,
  "gitlab": true,
  "gitter": true,
  "glass-cheers": true,
  "glass-martini": true,
  "glass-martini-alt": true,
  "glass-whiskey": true,
  "glasses": true,
  "glide": true,
  "glide-g": true,
  "globe": true,
  "globe-africa": true,
  "globe-americas": true,
  "globe-asia": true,
  "globe-europe": true,
  "gofore": true,
  "golf-ball": true,
  "goodreads": true,
  "goodreads-g": true,
  "google": true,
  "google-drive": true,
  "google-pay": true,
  "google-play": true,
  "google-plus": true,
  "google-plus-g": true,
  "google-plus-square": true,
  "google-wallet": true,
  "gopuram": true,
  "graduation-cap": true,
  "gratipay": true,
  "grav": true,
  "greater-than": true,
  "greater-than-equal": true,
  "grimace": true,
  "grin": true,
  "grin-alt": true,
  "grin-beam": true,
  "grin-beam-sweat": true,
  "grin-hearts": true,
  "grin-squint": true,
  "grin-squint-tears": true,
  "grin-stars": true,
  "grin-tears": true,
  "grin-tongue": true,
  "grin-tongue-squint": true,
  "grin-tongue-wink": true,
  "grin-wink": true,
  "grip-horizontal": true,
  "grip-lines": true,
  "grip-lines-vertical": true,
  "grip-vertical": true,
  "gripfire": true,
  "grunt": true,
  "guilded": true,
  "guitar": true,
  "gulp": true,
  "h-square": true,
  "hacker-news": true,
  "hacker-news-square": true,
  "hackerrank": true,
  "hamburger": true,
  "hammer": true,
  "hamsa": true,
  "hand-holding": true,
  "hand-holding-heart": true,
  "hand-holding-medical": true,
  "hand-holding-usd": true,
  "hand-holding-water": true,
  "hand-lizard": true,
  "hand-middle-finger": true,
  "hand-paper": true,
  "hand-peace": true,
  "hand-point-down": true,
  "hand-point-left": true,
  "hand-point-right": true,
  "hand-point-up": true,
  "hand-pointer": true,
  "hand-rock": true,
  "hand-scissors": true,
  "hand-sparkles": true,
  "hand-spock": true,
  "hands": true,
  "hands-helping": true,
  "hands-wash": true,
  "handshake": true,
  "handshake-alt-slash": true,
  "handshake-slash": true,
  "hanukiah": true,
  "hard-hat": true,
  "hashtag": true,
  "hat-cowboy": true,
  "hat-cowboy-side": true,
  "hat-wizard": true,
  "hdd": true,
  "head-side-cough": true,
  "head-side-cough-slash": true,
  "head-side-mask": true,
  "head-side-virus": true,
  "heading": true,
  "headphones": true,
  "headphones-alt": true,
  "headset": true,
  "heart": true,
  "heart-broken": true,
  "heartbeat": true,
  "helicopter": true,
  "highlighter": true,
  "hiking": true,
  "hippo": true,
  "hips": true,
  "hire-a-helper": true,
  "history": true,
  "hive": true,
  "hockey-puck": true,
  "holly-berry": true,
  "home": true,
  "hooli": true,
  "hornbill": true,
  "horse": true,
  "horse-head": true,
  "hospital": true,
  "hospital-alt": true,
  "hospital-symbol": true,
  "hospital-user": true,
  "hot-tub": true,
  "hotdog": true,
  "hotel": true,
  "hotjar": true,
  "hourglass": true,
  "hourglass-end": true,
  "hourglass-half": true,
  "hourglass-start": true,
  "house-damage": true,
  "house-user": true,
  "houzz": true,
  "hryvnia": true,
  "html5": true,
  "hubspot": true,
  "i-cursor": true,
  "ice-cream": true,
  "icicles": true,
  "icons": true,
  "id-badge": true,
  "id-card": true,
  "id-card-alt": true,
  "ideal": true,
  "igloo": true,
  "image": true,
  "images": true,
  "imdb": true,
  "inbox": true,
  "indent": true,
  "industry": true,
  "infinity": true,
  "info": true,
  "info-circle": true,
  "innosoft": true,
  "instagram": true,
  "instagram-square": true,
  "instalod": true,
  "intercom": true,
  "internet-explorer": true,
  "invision": true,
  "ioxhost": true,
  "italic": true,
  "itch-io": true,
  "itunes": true,
  "itunes-note": true,
  "java": true,
  "jedi": true,
  "jedi-order": true,
  "jenkins": true,
  "jira": true,
  "joget": true,
  "joint": true,
  "joomla": true,
  "journal-whills": true,
  "js": true,
  "js-square": true,
  "jsfiddle": true,
  "kaaba": true,
  "kaggle": true,
  "key": true,
  "keybase": true,
  "keyboard": true,
  "keycdn": true,
  "khanda": true,
  "kickstarter": true,
  "kickstarter-k": true,
  "kiss": true,
  "kiss-beam": true,
  "kiss-wink-heart": true,
  "kiwi-bird": true,
  "korvue": true,
  "landmark": true,
  "language": true,
  "laptop": true,
  "laptop-code": true,
  "laptop-house": true,
  "laptop-medical": true,
  "laravel": true,
  "lastfm": true,
  "lastfm-square": true,
  "laugh": true,
  "laugh-beam": true,
  "laugh-squint": true,
  "laugh-wink": true,
  "layer-group": true,
  "leaf": true,
  "leanpub": true,
  "lemon": true,
  "less": true,
  "less-than": true,
  "less-than-equal": true,
  "level-down-alt": true,
  "level-up-alt": true,
  "life-ring": true,
  "lightbulb": true,
  "line": true,
  "link": true,
  "linkedin": true,
  "linkedin-in": true,
  "linode": true,
  "linux": true,
  "lira-sign": true,
  "list": true,
  "list-alt": true,
  "list-ol": true,
  "list-ul": true,
  "location-arrow": true,
  "lock": true,
  "lock-open": true,
  "long-arrow-alt-down": true,
  "long-arrow-alt-left": true,
  "long-arrow-alt-right": true,
  "long-arrow-alt-up": true,
  "low-vision": true,
  "luggage-cart": true,
  "lungs": true,
  "lungs-virus": true,
  "lyft": true,
  "magento": true,
  "magic": true,
  "magnet": true,
  "mail-bulk": true,
  "mailchimp": true,
  "male": true,
  "mandalorian": true,
  "map": true,
  "map-marked": true,
  "map-marked-alt": true,
  "map-marker": true,
  "map-marker-alt": true,
  "map-pin": true,
  "map-signs": true,
  "markdown": true,
  "marker": true,
  "mars": true,
  "mars-double": true,
  "mars-stroke": true,
  "mars-stroke-h": true,
  "mars-stroke-v": true,
  "mask": true,
  "mastodon": true,
  "maxcdn": true,
  "mdb": true,
  "medal": true,
  "medapps": true,
  "medium": true,
  "medium-m": true,
  "medkit": true,
  "medrt": true,
  "meetup": true,
  "megaport": true,
  "meh": true,
  "meh-blank": true,
  "meh-rolling-eyes": true,
  "memory": true,
  "mendeley": true,
  "menorah": true,
  "mercury": true,
  "meteor": true,
  "microblog": true,
  "microchip": true,
  "microphone": true,
  "microphone-alt": true,
  "microphone-alt-slash": true,
  "microphone-slash": true,
  "microscope": true,
  "microsoft": true,
  "minus": true,
  "minus-circle": true,
  "minus-square": true,
  "mitten": true,
  "mix": true,
  "mixcloud": true,
  "mixer": true,
  "mizuni": true,
  "mobile": true,
  "mobile-alt": true,
  "modx": true,
  "monero": true,
  "money-bill": true,
  "money-bill-alt": true,
  "money-bill-wave": true,
  "money-bill-wave-alt": true,
  "money-check": true,
  "money-check-alt": true,
  "monument": true,
  "moon": true,
  "mortar-pestle": true,
  "mosque": true,
  "motorcycle": true,
  "mountain": true,
  "mouse": true,
  "mouse-pointer": true,
  "mug-hot": true,
  "music": true,
  "napster": true,
  "neos": true,
  "network-wired": true,
  "neuter": true,
  "newspaper": true,
  "nimblr": true,
  "node": true,
  "node-js": true,
  "not-equal": true,
  "notes-medical": true,
  "npm": true,
  "ns8": true,
  "nutritionix": true,
  "object-group": true,
  "object-ungroup": true,
  "octopus-deploy": true,
  "odnoklassniki": true,
  "odnoklassniki-square": true,
  "oil-can": true,
  "old-republic": true,
  "om": true,
  "opencart": true,
  "openid": true,
  "opera": true,
  "optin-monster": true,
  "orcid": true,
  "osi": true,
  "otter": true,
  "outdent": true,
  "page4": true,
  "pagelines": true,
  "pager": true,
  "paint-brush": true,
  "paint-roller": true,
  "palette": true,
  "palfed": true,
  "pallet": true,
  "paper-plane": true,
  "paperclip": true,
  "parachute-box": true,
  "paragraph": true,
  "parking": true,
  "passport": true,
  "pastafarianism": true,
  "paste": true,
  "patreon": true,
  "pause": true,
  "pause-circle": true,
  "paw": true,
  "paypal": true,
  "peace": true,
  "pen": true,
  "pen-alt": true,
  "pen-fancy": true,
  "pen-nib": true,
  "pen-square": true,
  "pencil-alt": true,
  "pencil-ruler": true,
  "penny-arcade": true,
  "people-arrows": true,
  "people-carry": true,
  "pepper-hot": true,
  "perbyte": true,
  "percent": true,
  "percentage": true,
  "periscope": true,
  "person-booth": true,
  "phabricator": true,
  "phoenix-framework": true,
  "phoenix-squadron": true,
  "phone": true,
  "phone-alt": true,
  "phone-slash": true,
  "phone-square": true,
  "phone-square-alt": true,
  "phone-volume": true,
  "photo-video": true,
  "php": true,
  "pied-piper": true,
  "pied-piper-alt": true,
  "pied-piper-hat": true,
  "pied-piper-pp": true,
  "pied-piper-square": true,
  "piggy-bank": true,
  "pills": true,
  "pinterest": true,
  "pinterest-p": true,
  "pinterest-square": true,
  "pizza-slice": true,
  "place-of-worship": true,
  "plane": true,
  "plane-arrival": true,
  "plane-departure": true,
  "plane-slash": true,
  "play": true,
  "play-circle": true,
  "playstation": true,
  "plug": true,
  "plus": true,
  "plus-circle": true,
  "plus-square": true,
  "podcast": true,
  "poll": true,
  "poll-h": true,
  "poo": true,
  "poo-storm": true,
  "poop": true,
  "portrait": true,
  "pound-sign": true,
  "power-off": true,
  "pray": true,
  "praying-hands": true,
  "prescription": true,
  "prescription-bottle": true,
  "prescription-bottle-alt": true,
  "print": true,
  "procedures": true,
  "product-hunt": true,
  "project-diagram": true,
  "pump-medical": true,
  "pump-soap": true,
  "pushed": true,
  "puzzle-piece": true,
  "python": true,
  "qq": true,
  "qrcode": true,
  "question": true,
  "question-circle": true,
  "quidditch": true,
  "quinscape": true,
  "quora": true,
  "quote-left": true,
  "quote-right": true,
  "quran": true,
  "r-project": true,
  "radiation": true,
  "radiation-alt": true,
  "rainbow": true,
  "random": true,
  "raspberry-pi": true,
  "ravelry": true,
  "react": true,
  "reacteurope": true,
  "readme": true,
  "rebel": true,
  "receipt": true,
  "record-vinyl": true,
  "recycle": true,
  "red-river": true,
  "reddit": true,
  "reddit-alien": true,
  "reddit-square": true,
  "redhat": true,
  "redo": true,
  "redo-alt": true,
  "registered": true,
  "remove-format": true,
  "renren": true,
  "reply": true,
  "reply-all": true,
  "replyd": true,
  "republican": true,
  "researchgate": true,
  "resolving": true,
  "restroom": true,
  "retweet": true,
  "rev": true,
  "ribbon": true,
  "ring": true,
  "road": true,
  "robot": true,
  "rocket": true,
  "rocketchat": true,
  "rockrms": true,
  "route": true,
  "rss": true,
  "rss-square": true,
  "ruble-sign": true,
  "ruler": true,
  "ruler-combined": true,
  "ruler-horizontal": true,
  "ruler-vertical": true,
  "running": true,
  "rupee-sign": true,
  "rust": true,
  "sad-cry": true,
  "sad-tear": true,
  "safari": true,
  "salesforce": true,
  "sass": true,
  "satellite": true,
  "satellite-dish": true,
  "save": true,
  "schlix": true,
  "school": true,
  "screwdriver": true,
  "scribd": true,
  "scroll": true,
  "sd-card": true,
  "search": true,
  "search-dollar": true,
  "search-location": true,
  "search-minus": true,
  "search-plus": true,
  "searchengin": true,
  "seedling": true,
  "sellcast": true,
  "sellsy": true,
  "server": true,
  "servicestack": true,
  "shapes": true,
  "share": true,
  "share-alt": true,
  "share-alt-square": true,
  "share-square": true,
  "shekel-sign": true,
  "shield-alt": true,
  "shield-virus": true,
  "ship": true,
  "shipping-fast": true,
  "shirtsinbulk": true,
  "shoe-prints": true,
  "shopify": true,
  "shopping-bag": true,
  "shopping-basket": true,
  "shopping-cart": true,
  "shopware": true,
  "shower": true,
  "shuttle-van": true,
  "sign": true,
  "sign-in-alt": true,
  "sign-language": true,
  "sign-out-alt": true,
  "signal": true,
  "signature": true,
  "sim-card": true,
  "simplybuilt": true,
  "sink": true,
  "sistrix": true,
  "sitemap": true,
  "sith": true,
  "skating": true,
  "sketch": true,
  "skiing": true,
  "skiing-nordic": true,
  "skull": true,
  "skull-crossbones": true,
  "skyatlas": true,
  "skype": true,
  "slack": true,
  "slack-hash": true,
  "slash": true,
  "sleigh": true,
  "sliders-h": true,
  "slideshare": true,
  "smile": true,
  "smile-beam": true,
  "smile-wink": true,
  "smog": true,
  "smoking": true,
  "smoking-ban": true,
  "sms": true,
  "snapchat": true,
  "snapchat-ghost": true,
  "snapchat-square": true,
  "snowboarding": true,
  "snowflake": true,
  "snowman": true,
  "snowplow": true,
  "soap": true,
  "socks": true,
  "solar-panel": true,
  "sort": true,
  "sort-alpha-down": true,
  "sort-alpha-down-alt": true,
  "sort-alpha-up": true,
  "sort-alpha-up-alt": true,
  "sort-amount-down": true,
  "sort-amount-down-alt": true,
  "sort-amount-up": true,
  "sort-amount-up-alt": true,
  "sort-down": true,
  "sort-numeric-down": true,
  "sort-numeric-down-alt": true,
  "sort-numeric-up": true,
  "sort-numeric-up-alt": true,
  "sort-up": true,
  "soundcloud": true,
  "sourcetree": true,
  "spa": true,
  "space-shuttle": true,
  "speakap": true,
  "speaker-deck": true,
  "spell-check": true,
  "spider": true,
  "spinner": true,
  "splotch": true,
  "spotify": true,
  "spray-can": true,
  "square": true,
  "square-full": true,
  "square-root-alt": true,
  "squarespace": true,
  "stack-exchange": true,
  "stack-overflow": true,
  "stackpath": true,
  "stamp": true,
  "star": true,
  "star-and-crescent": true,
  "star-half": true,
  "star-half-alt": true,
  "star-of-david": true,
  "star-of-life": true,
  "staylinked": true,
  "steam": true,
  "steam-square": true,
  "steam-symbol": true,
  "step-backward": true,
  "step-forward": true,
  "stethoscope": true,
  "sticker-mule": true,
  "sticky-note": true,
  "stop": true,
  "stop-circle": true,
  "stopwatch": true,
  "stopwatch-20": true,
  "store": true,
  "store-alt": true,
  "store-alt-slash": true,
  "store-slash": true,
  "strava": true,
  "stream": true,
  "street-view": true,
  "strikethrough": true,
  "stripe": true,
  "stripe-s": true,
  "stroopwafel": true,
  "studiovinari": true,
  "stumbleupon": true,
  "stumbleupon-circle": true,
  "subscript": true,
  "subway": true,
  "suitcase": true,
  "suitcase-rolling": true,
  "sun": true,
  "superpowers": true,
  "superscript": true,
  "supple": true,
  "surprise": true,
  "suse": true,
  "swatchbook": true,
  "swift": true,
  "swimmer": true,
  "swimming-pool": true,
  "symfony": true,
  "synagogue": true,
  "sync": true,
  "sync-alt": true,
  "syringe": true,
  "table": true,
  "table-tennis": true,
  "tablet": true,
  "tablet-alt": true,
  "tablets": true,
  "tachometer-alt": true,
  "tag": true,
  "tags": true,
  "tape": true,
  "tasks": true,
  "taxi": true,
  "teamspeak": true,
  "teeth": true,
  "teeth-open": true,
  "telegram": true,
  "telegram-plane": true,
  "temperature-high": true,
  "temperature-low": true,
  "tencent-weibo": true,
  "tenge": true,
  "terminal": true,
  "text-height": true,
  "text-width": true,
  "th": true,
  "th-large": true,
  "th-list": true,
  "the-red-yeti": true,
  "theater-masks": true,
  "themeco": true,
  "themeisle": true,
  "thermometer": true,
  "thermometer-empty": true,
  "thermometer-full": true,
  "thermometer-half": true,
  "thermometer-quarter": true,
  "thermometer-three-quarters": true,
  "think-peaks": true,
  "thumbs-down": true,
  "thumbs-up": true,
  "thumbtack": true,
  "ticket-alt": true,
  "tiktok": true,
  "times": true,
  "times-circle": true,
  "tint": true,
  "tint-slash": true,
  "tired": true,
  "toggle-off": true,
  "toggle-on": true,
  "toilet": true,
  "toilet-paper": true,
  "toilet-paper-slash": true,
  "toolbox": true,
  "tools": true,
  "tooth": true,
  "torah": true,
  "torii-gate": true,
  "tractor": true,
  "trade-federation": true,
  "trademark": true,
  "traffic-light": true,
  "trailer": true,
  "train": true,
  "tram": true,
  "transgender": true,
  "transgender-alt": true,
  "trash": true,
  "trash-alt": true,
  "trash-restore": true,
  "trash-restore-alt": true,
  "tree": true,
  "trello": true,
  "trophy": true,
  "truck": true,
  "truck-loading": true,
  "truck-monster": true,
  "truck-moving": true,
  "truck-pickup": true,
  "tshirt": true,
  "tty": true,
  "tumblr": true,
  "tumblr-square": true,
  "tv": true,
  "twitch": true,
  "twitter": true,
  "twitter-square": true,
  "typo3": true,
  "uber": true,
  "ubuntu": true,
  "uikit": true,
  "umbraco": true,
  "umbrella": true,
  "umbrella-beach": true,
  "uncharted": true,
  "underline": true,
  "undo": true,
  "undo-alt": true,
  "uniregistry": true,
  "unity": true,
  "universal-access": true,
  "university": true,
  "unlink": true,
  "unlock": true,
  "unlock-alt": true,
  "unsplash": true,
  "untappd": true,
  "upload": true,
  "ups": true,
  "usb": true,
  "user": true,
  "user-alt": true,
  "user-alt-slash": true,
  "user-astronaut": true,
  "user-check": true,
  "user-circle": true,
  "user-clock": true,
  "user-cog": true,
  "user-edit": true,
  "user-friends": true,
  "user-graduate": true,
  "user-injured": true,
  "user-lock": true,
  "user-md": true,
  "user-minus": true,
  "user-ninja": true,
  "user-nurse": true,
  "user-plus": true,
  "user-secret": true,
  "user-shield": true,
  "user-slash": true,
  "user-tag": true,
  "user-tie": true,
  "user-times": true,
  "users": true,
  "users-cog": true,
  "users-slash": true,
  "usps": true,
  "ussunnah": true,
  "utensil-spoon": true,
  "utensils": true,
  "vaadin": true,
  "vector-square": true,
  "venus": true,
  "venus-double": true,
  "venus-mars": true,
  "vest": true,
  "vest-patches": true,
  "viacoin": true,
  "viadeo": true,
  "viadeo-square": true,
  "vial": true,
  "vials": true,
  "viber": true,
  "video": true,
  "video-slash": true,
  "vihara": true,
  "vimeo": true,
  "vimeo-square": true,
  "vimeo-v": true,
  "vine": true,
  "virus": true,
  "virus-slash": true,
  "viruses": true,
  "vk": true,
  "vnv": true,
  "voicemail": true,
  "volleyball-ball": true,
  "volume-down": true,
  "volume-mute": true,
  "volume-off": true,
  "volume-up": true,
  "vote-yea": true,
  "vr-cardboard": true,
  "vuejs": true,
  "walking": true,
  "wallet": true,
  "warehouse": true,
  "watchman-monitoring": true,
  "water": true,
  "wave-square": true,
  "waze": true,
  "weebly": true,
  "weibo": true,
  "weight": true,
  "weight-hanging": true,
  "weixin": true,
  "whatsapp": true,
  "whatsapp-square": true,
  "wheelchair": true,
  "whmcs": true,
  "wifi": true,
  "wikipedia-w": true,
  "wind": true,
  "window-close": true,
  "window-maximize": true,
  "window-minimize": true,
  "window-restore": true,
  "windows": true,
  "wine-bottle": true,
  "wine-glass": true,
  "wine-glass-alt": true,
  "wix": true,
  "wizards-of-the-coast": true,
  "wodu": true,
  "wolf-pack-battalion": true,
  "won-sign": true,
  "wordpress": true,
  "wordpress-simple": true,
  "wpbeginner": true,
  "wpexplorer": true,
  "wpforms": true,
  "wpressr": true,
  "wrench": true,
  "x-ray": true,
  "xbox": true,
  "xing": true,
  "xing-square": true,
  "y-combinator": true,
  "yahoo": true,
  "yammer": true,
  "yandex": true,
  "yandex-international": true,
  "yarn": true,
  "yelp": true,
  "yen-sign": true,
  "yin-yang": true,
  "yoast": true,
  "youtube": true,
  "youtube-square": true,
  "zhihu": true
}
